compliance_vision/__init__.py
compliance_vision/main.py
compliance_vision-0.1.0.dist-info/METADATA
compliance_vision-0.1.0.dist-info/WHEEL
compliance_vision-0.1.0.dist-info/entry_points.txt
compliance_vision-0.1.0.dist-info/RECORD
