Metadata-Version: 2.4
Name: compliance-vision
Version: 0.1.0
Summary: Add your description here
Author-email: huangyp3gd <huangyp3.gd@chinatelecom.cn>
Requires-Python: >=3.13
Requires-Dist: openai
